woodchuck/__init__.py
woodchuck_shwinhs-1.0.0.dist-info/METADATA
woodchuck_shwinhs-1.0.0.dist-info/WHEEL
woodchuck_shwinhs-1.0.0.dist-info/top_level.txt
woodchuck_shwinhs-1.0.0.dist-info/RECORD
