Metadata-Version: 2.1
Name: woodchuck-shwinhs
Version: 1.0.0
Summary: A lightweight, opinionated Python logging package.
Home-page: https://github.com/ShwinHS/woodchuck.git
Author: Ashwin Mahadevan
License: UNKNOWN
Platform: UNKNOWN
Requires-Python: >=3.8
